{
  "id": "SCES-00062",
  "title": "Warhawk - The Red Mercury Missions",
  "discs": 1,
  "languages": [
    "en"
  ],
  "link": "http://psxdatacenter.com/games/P/W/SCES-00062.html",
  "coverLink": "http://psxdatacenter.com/images/covers/P/W/SCES-00062.jpg",
  "commonTitle": "Warhawk - The Red Mercury Missions / Warhawk",
  "genre": "Action",
  "style": "Shooter",
  "rating": [
    "elspa-3",
    "usk-0"
  ],
  "developer": "SingleTrac",
  "publisher": "Sony Computer Entertainment Europe",
  "date": "1995-11-10"
}
