{
  "id": [
    "SLES-03349",
    "SLES-13349"
  ],
  "title": "Dracula 2 - Le Dernier Sanctuaire",
  "discs": 2,
  "languages": [
    "fr"
  ],
  "link": "http://psxdatacenter.com/games/P/D/SLES-03349.html",
  "coverLink": "http://psxdatacenter.com/images/covers/P/D/SLES-03349.jpg",
  "genre": "Adventure  ( First Person perspective )",
  "rating": [
    "elspa-3",
    "usk-0"
  ],
  "developer": "Visual Impact Productions",
  "publisher": "The Adventure Company / Canal + Multimedia / France Multimedia",
  "date": "2002-06-10"
}
