{
  "id": [
    "SCPS-10116",
    "SCPS-10117"
  ],
  "title": "Gran Turismo 2 - The Real Driving Simulator",
  "includes": "Arcade Disc + Simulation Disc",
  "discs": 2,
  "languages": [
    "jp"
  ],
  "link": "http://psxdatacenter.com/games/J/G/SCPS-10116.html",
  "coverLink": "http://psxdatacenter.com/images/covers/J/G/SCPS-10116.jpg",
  "genre": "Driving",
  "style": "Racing",
  "rating": [
    "esrb-e",
    "usk-0"
  ],
  "developer": "Polyphony Digital",
  "publisher": "Sony",
  "date": "1999-12-11"
}
