{
  "id": "SLES-53099",
  "title": "Pilot Down - Behind Enemy Lines",
  "discs": 1,
  "languages": [
    "en",
    "fr",
    "de",
    "it",
    "es"
  ],
  "link": "http://psxdatacenter.com/psx2/games2/SLES-53099.html",
  "coverLink": "http://psxdatacenter.com/psx2/images2/covers/SLES-53099.jpg",
  "genre": "Action",
  "style": "Shooter",
  "rating": [
    "elspa-16",
    "usk-0"
  ],
  "developer": "Wide Games / Kuju Entertainment",
  "publisher": "Oxygen Interactive",
  "date": "2005-09-09"
}
