{
  "id": [
    "SLUS-01251",
    "SLUS-01295",
    "SLUS-01296",
    "SLUS-01297"
  ],
  "title": "Final Fantasy IX",
  "discs": 4,
  "languages": [
    "en"
  ],
  "link": "http://psxdatacenter.com/games/U/F/SLUS-01251.html",
  "coverLink": "http://psxdatacenter.com/images/covers/U/F/SLUS-01251.jpg",
  "commonTitle": "Final Fantasy IX / FF9 / FFIX",
  "genre": "RPG",
  "rating": [
    "esrb-t",
    "usk-0"
  ],
  "developer": "Squaresoft",
  "publisher": "Squaresoft",
  "date": "2000-11-15"
}
